{
    "swagger": "2.0",
    "info": {
        "description": "A web-based short video platform",
        "title": "Traceability",
        "contact": {},
        "version": "0.0.1"
    },
    "paths": {
        "/api/v1/auth/video/feed": {
            "get": {
                "description": "获取视频feed流",
                "summary": "获取视频feed流",
                "parameters": [
                    {
                        "type": "string",
                        "description": "token",
                        "name": "token",
                        "in": "header",
                        "required": true
                    },
                    {
                        "type": "integer",
                        "description": "feed类型",
                        "name": "type",
                        "in": "query",
                        "required": true
                    },
                    {
                        "type": "integer",
                        "description": "最新时间",
                        "name": "latest_time",
                        "in": "query",
                        "required": true
                    }
                ],
                "responses": {
                    "200": {
                        "description": "OK",
                        "schema": {
                            "type": "string"
                        }
                    },
                    "400": {
                        "description": "Bad Request",
                        "schema": {
                            "type": "string"
                        }
                    }
                }
            }
        },
        "/api/v1/collect/action": {
            "post": {
                "description": "用户收藏操作",
                "summary": "用户收藏操作",
                "parameters": [
                    {
                        "type": "string",
                        "description": "token",
                        "name": "token",
                        "in": "header",
                        "required": true
                    },
                    {
                        "type": "integer",
                        "description": "视频id",
                        "name": "video_id",
                        "in": "formData",
                        "required": true
                    },
                    {
                        "type": "integer",
                        "description": "操作类型 1:收藏 2:取消收藏",
                        "name": "action_type",
                        "in": "formData",
                        "required": true
                    }
                ],
                "responses": {
                    "200": {
                        "description": "OK",
                        "schema": {
                            "type": "string"
                        }
                    },
                    "400": {
                        "description": "Bad Request",
                        "schema": {
                            "type": "string"
                        }
                    }
                }
            }
        },
        "/api/v1/collect/list": {
            "get": {
                "description": "获取用户收藏列表",
                "summary": "获取用户收藏列表",
                "parameters": [
                    {
                        "type": "string",
                        "description": "token",
                        "name": "token",
                        "in": "header",
                        "required": true
                    },
                    {
                        "type": "integer",
                        "description": "用户id",
                        "name": "user_id",
                        "in": "query",
                        "required": true
                    }
                ],
                "responses": {
                    "200": {
                        "description": "OK",
                        "schema": {
                            "type": "string"
                        }
                    },
                    "400": {
                        "description": "Bad Request",
                        "schema": {
                            "type": "string"
                        }
                    }
                }
            }
        },
        "/api/v1/comment/add": {
            "post": {
                "description": "添加评论",
                "summary": "添加评论",
                "parameters": [
                    {
                        "type": "string",
                        "description": "token",
                        "name": "token",
                        "in": "header",
                        "required": true
                    },
                    {
                        "type": "integer",
                        "description": "视频id",
                        "name": "video_id",
                        "in": "formData",
                        "required": true
                    },
                    {
                        "type": "string",
                        "description": "评论内容",
                        "name": "content",
                        "in": "formData"
                    }
                ],
                "responses": {
                    "200": {
                        "description": "OK",
                        "schema": {
                            "type": "string"
                        }
                    },
                    "400": {
                        "description": "Bad Request",
                        "schema": {
                            "type": "string"
                        }
                    }
                }
            }
        },
        "/api/v1/comment/delete": {
            "post": {
                "description": "删除评论",
                "summary": "删除评论",
                "parameters": [
                    {
                        "type": "string",
                        "description": "token",
                        "name": "token",
                        "in": "header",
                        "required": true
                    },
                    {
                        "type": "integer",
                        "description": "评论id",
                        "name": "comment_id",
                        "in": "formData",
                        "required": true
                    }
                ],
                "responses": {
                    "200": {
                        "description": "OK",
                        "schema": {
                            "type": "string"
                        }
                    },
                    "400": {
                        "description": "Bad Request",
                        "schema": {
                            "type": "string"
                        }
                    }
                }
            }
        },
        "/api/v1/like/action": {
            "post": {
                "description": "用户喜爱操作",
                "summary": "用户喜爱操作",
                "parameters": [
                    {
                        "type": "string",
                        "description": "token",
                        "name": "token",
                        "in": "header",
                        "required": true
                    },
                    {
                        "type": "integer",
                        "description": "视频id",
                        "name": "video_id",
                        "in": "formData",
                        "required": true
                    },
                    {
                        "type": "integer",
                        "description": "操作类型 1:喜爱 2:取消喜爱",
                        "name": "action_type",
                        "in": "formData",
                        "required": true
                    }
                ],
                "responses": {
                    "200": {
                        "description": "OK",
                        "schema": {
                            "type": "string"
                        }
                    },
                    "400": {
                        "description": "Bad Request",
                        "schema": {
                            "type": "string"
                        }
                    }
                }
            }
        },
        "/api/v1/like/list": {
            "get": {
                "description": "获取用户点赞列表",
                "summary": "获取用户点赞列表",
                "parameters": [
                    {
                        "type": "string",
                        "description": "token",
                        "name": "token",
                        "in": "header",
                        "required": true
                    },
                    {
                        "type": "integer",
                        "description": "用户id",
                        "name": "user_id",
                        "in": "query",
                        "required": true
                    }
                ],
                "responses": {
                    "200": {
                        "description": "OK",
                        "schema": {
                            "type": "string"
                        }
                    },
                    "400": {
                        "description": "Bad Request",
                        "schema": {
                            "type": "string"
                        }
                    }
                }
            }
        },
        "/api/v1/message/chat": {
            "get": {
                "description": "获取消息列表",
                "summary": "获取消息列表",
                "parameters": [
                    {
                        "type": "string",
                        "description": "token",
                        "name": "token",
                        "in": "header",
                        "required": true
                    },
                    {
                        "type": "integer",
                        "description": "目标用户id",
                        "name": "to_user_id",
                        "in": "query",
                        "required": true
                    }
                ],
                "responses": {
                    "200": {
                        "description": "OK",
                        "schema": {
                            "type": "string"
                        }
                    },
                    "400": {
                        "description": "Bad Request",
                        "schema": {
                            "type": "string"
                        }
                    }
                }
            }
        },
        "/api/v1/message/open": {
            "get": {
                "description": "获取用户开放消息列表",
                "summary": "获取用户开放消息列表",
                "parameters": [
                    {
                        "type": "string",
                        "description": "token",
                        "name": "token",
                        "in": "header",
                        "required": true
                    }
                ],
                "responses": {
                    "200": {
                        "description": "OK",
                        "schema": {
                            "type": "string"
                        }
                    },
                    "400": {
                        "description": "Bad Request",
                        "schema": {
                            "type": "string"
                        }
                    }
                }
            }
        },
        "/api/v1/message/open/add": {
            "post": {
                "description": "添加开放联系人",
                "summary": "添加开放联系人",
                "parameters": [
                    {
                        "type": "string",
                        "description": "token",
                        "name": "token",
                        "in": "header",
                        "required": true
                    },
                    {
                        "type": "integer",
                        "description": "开放联系人id",
                        "name": "open_user_id",
                        "in": "formData",
                        "required": true
                    }
                ],
                "responses": {
                    "200": {
                        "description": "OK",
                        "schema": {
                            "type": "string"
                        }
                    },
                    "400": {
                        "description": "Bad Request",
                        "schema": {
                            "type": "string"
                        }
                    }
                }
            }
        },
        "/api/v1/message/open/delete": {
            "post": {
                "description": "删除开放联系人",
                "summary": "删除开放联系人",
                "parameters": [
                    {
                        "type": "string",
                        "description": "token",
                        "name": "token",
                        "in": "header",
                        "required": true
                    },
                    {
                        "type": "integer",
                        "description": "开放联系人id",
                        "name": "open_user_id",
                        "in": "formData",
                        "required": true
                    }
                ],
                "responses": {
                    "200": {
                        "description": "OK",
                        "schema": {
                            "type": "string"
                        }
                    },
                    "400": {
                        "description": "Bad Request",
                        "schema": {
                            "type": "string"
                        }
                    }
                }
            }
        },
        "/api/v1/message/send": {
            "post": {
                "description": "发送消息(暂时设置为不互相关注也能发消息)",
                "summary": "发送消息",
                "parameters": [
                    {
                        "type": "string",
                        "description": "token",
                        "name": "token",
                        "in": "header",
                        "required": true
                    },
                    {
                        "type": "integer",
                        "description": "目标用户id",
                        "name": "to_user_id",
                        "in": "formData",
                        "required": true
                    },
                    {
                        "type": "string",
                        "description": "消息内容",
                        "name": "content",
                        "in": "formData",
                        "required": true
                    }
                ],
                "responses": {
                    "200": {
                        "description": "OK",
                        "schema": {
                            "type": "string"
                        }
                    },
                    "400": {
                        "description": "Bad Request",
                        "schema": {
                            "type": "string"
                        }
                    }
                }
            }
        },
        "/api/v1/public/comment/list": {
            "get": {
                "description": "获取评论列表",
                "summary": "获取评论列表",
                "parameters": [
                    {
                        "type": "integer",
                        "description": "页码",
                        "name": "page",
                        "in": "query"
                    },
                    {
                        "type": "integer",
                        "description": "每页数量",
                        "name": "limit",
                        "in": "query"
                    },
                    {
                        "type": "integer",
                        "description": "视频id",
                        "name": "video_id",
                        "in": "query",
                        "required": true
                    }
                ],
                "responses": {
                    "200": {
                        "description": "OK",
                        "schema": {
                            "type": "string"
                        }
                    },
                    "400": {
                        "description": "Bad Request",
                        "schema": {
                            "type": "string"
                        }
                    }
                }
            }
        },
        "/api/v1/public/user/login": {
            "post": {
                "description": "用户登录",
                "summary": "用户登录",
                "parameters": [
                    {
                        "type": "string",
                        "description": "用户名",
                        "name": "username",
                        "in": "formData",
                        "required": true
                    },
                    {
                        "type": "string",
                        "description": "密码",
                        "name": "password",
                        "in": "formData",
                        "required": true
                    }
                ],
                "responses": {
                    "200": {
                        "description": "OK",
                        "schema": {
                            "type": "string"
                        }
                    },
                    "400": {
                        "description": "Bad Request",
                        "schema": {
                            "type": "string"
                        }
                    },
                    "401": {
                        "description": "Unauthorized",
                        "schema": {
                            "type": "string"
                        }
                    }
                }
            }
        },
        "/api/v1/public/user/register": {
            "post": {
                "description": "用户注册",
                "summary": "用户注册",
                "parameters": [
                    {
                        "type": "string",
                        "description": "用户名",
                        "name": "username",
                        "in": "formData",
                        "required": true
                    },
                    {
                        "type": "string",
                        "description": "旧密码",
                        "name": "password",
                        "in": "formData",
                        "required": true
                    },
                    {
                        "type": "string",
                        "description": "新密码",
                        "name": "new_password",
                        "in": "formData",
                        "required": true
                    },
                    {
                        "type": "string",
                        "description": "邮箱",
                        "name": "email",
                        "in": "formData"
                    },
                    {
                        "type": "string",
                        "description": "手机号",
                        "name": "mobile",
                        "in": "formData"
                    }
                ],
                "responses": {
                    "200": {
                        "description": "OK",
                        "schema": {
                            "type": "string"
                        }
                    },
                    "400": {
                        "description": "Bad Request",
                        "schema": {
                            "type": "string"
                        }
                    }
                }
            }
        },
        "/api/v1/public/video/search": {
            "get": {
                "description": "获取视频搜索结果",
                "summary": "获取视频搜索结果",
                "parameters": [
                    {
                        "type": "string",
                        "description": "搜索关键字",
                        "name": "key",
                        "in": "query",
                        "required": true
                    },
                    {
                        "type": "integer",
                        "description": "搜索类型",
                        "name": "type",
                        "in": "query",
                        "required": true
                    }
                ],
                "responses": {
                    "200": {
                        "description": "OK",
                        "schema": {
                            "type": "string"
                        }
                    },
                    "400": {
                        "description": "Bad Request",
                        "schema": {
                            "type": "string"
                        }
                    }
                }
            }
        },
        "/api/v1/relation/action": {
            "post": {
                "description": "关注/取消关注",
                "summary": "关注/取消关注",
                "parameters": [
                    {
                        "type": "string",
                        "description": "token",
                        "name": "token",
                        "in": "header",
                        "required": true
                    },
                    {
                        "type": "integer",
                        "description": "1:关注 2:取消关注",
                        "name": "action_type",
                        "in": "formData",
                        "required": true
                    },
                    {
                        "type": "integer",
                        "description": "想要关注/取关的用户ID",
                        "name": "user_id",
                        "in": "formData",
                        "required": true
                    }
                ],
                "responses": {
                    "200": {
                        "description": "OK",
                        "schema": {
                            "type": "string"
                        }
                    },
                    "400": {
                        "description": "Bad Request",
                        "schema": {
                            "type": "string"
                        }
                    }
                }
            }
        },
        "/api/v1/relation/fans/list": {
            "get": {
                "description": "粉丝列表",
                "summary": "粉丝列表",
                "parameters": [
                    {
                        "type": "string",
                        "description": "token",
                        "name": "token",
                        "in": "header",
                        "required": true
                    },
                    {
                        "type": "integer",
                        "description": "用户ID",
                        "name": "user_id",
                        "in": "query",
                        "required": true
                    }
                ],
                "responses": {
                    "200": {
                        "description": "OK",
                        "schema": {
                            "type": "string"
                        }
                    },
                    "400": {
                        "description": "Bad Request",
                        "schema": {
                            "type": "string"
                        }
                    }
                }
            }
        },
        "/api/v1/relation/focus/list": {
            "get": {
                "description": "关注列表",
                "summary": "关注列表",
                "parameters": [
                    {
                        "type": "string",
                        "description": "token",
                        "name": "token",
                        "in": "header",
                        "required": true
                    },
                    {
                        "type": "integer",
                        "description": "用户ID",
                        "name": "user_id",
                        "in": "query",
                        "required": true
                    }
                ],
                "responses": {
                    "200": {
                        "description": "OK",
                        "schema": {
                            "type": "string"
                        }
                    },
                    "400": {
                        "description": "Bad Request",
                        "schema": {
                            "type": "string"
                        }
                    }
                }
            }
        },
        "/api/v1/system/cpu/usage": {
            "get": {
                "summary": "获取CPU使用率",
                "parameters": [
                    {
                        "type": "string",
                        "description": "token",
                        "name": "token",
                        "in": "header",
                        "required": true
                    }
                ],
                "responses": {
                    "200": {
                        "description": "OK",
                        "schema": {
                            "$ref": "#/definitions/api.Response"
                        }
                    },
                    "400": {
                        "description": "Bad Request",
                        "schema": {
                            "$ref": "#/definitions/api.Response"
                        }
                    }
                }
            }
        },
        "/api/v1/system/memory/usage": {
            "get": {
                "summary": "获取内存使用率",
                "parameters": [
                    {
                        "type": "string",
                        "description": "token",
                        "name": "token",
                        "in": "header",
                        "required": true
                    }
                ],
                "responses": {
                    "200": {
                        "description": "OK",
                        "schema": {
                            "$ref": "#/definitions/api.Response"
                        }
                    },
                    "400": {
                        "description": "Bad Request",
                        "schema": {
                            "$ref": "#/definitions/api.Response"
                        }
                    }
                }
            }
        },
        "/api/v1/user/": {
            "get": {
                "description": "获取用户信息",
                "summary": "获取用户信息",
                "parameters": [
                    {
                        "type": "string",
                        "description": "token",
                        "name": "token",
                        "in": "header",
                        "required": true
                    },
                    {
                        "type": "integer",
                        "description": "用户id",
                        "name": "user_id",
                        "in": "query",
                        "required": true
                    }
                ],
                "responses": {
                    "200": {
                        "description": "OK",
                        "schema": {
                            "type": "string"
                        }
                    },
                    "400": {
                        "description": "Bad Request",
                        "schema": {
                            "type": "string"
                        }
                    }
                }
            }
        },
        "/api/v1/user/delete": {
            "post": {
                "description": "删除用户",
                "summary": "删除用户",
                "parameters": [
                    {
                        "type": "string",
                        "description": "token",
                        "name": "token",
                        "in": "header",
                        "required": true
                    },
                    {
                        "type": "integer",
                        "description": "用户id",
                        "name": "user_id",
                        "in": "formData",
                        "required": true
                    }
                ],
                "responses": {
                    "200": {
                        "description": "OK",
                        "schema": {
                            "type": "string"
                        }
                    },
                    "400": {
                        "description": "Bad Request",
                        "schema": {
                            "type": "string"
                        }
                    }
                }
            }
        },
        "/api/v1/user/increase": {
            "get": {
                "description": "获取月总日用户增长记录列表",
                "summary": "获取月总日用户增长记录列表",
                "parameters": [
                    {
                        "type": "string",
                        "description": "token",
                        "name": "token",
                        "in": "header",
                        "required": true
                    },
                    {
                        "type": "string",
                        "description": "年份",
                        "name": "year",
                        "in": "query",
                        "required": true
                    },
                    {
                        "type": "string",
                        "description": "月份",
                        "name": "month",
                        "in": "query",
                        "required": true
                    }
                ],
                "responses": {
                    "200": {
                        "description": "OK",
                        "schema": {
                            "type": "string"
                        }
                    },
                    "400": {
                        "description": "Bad Request",
                        "schema": {
                            "type": "string"
                        }
                    }
                }
            }
        },
        "/api/v1/user/list": {
            "get": {
                "description": "获取用户列表",
                "summary": "获取用户列表",
                "parameters": [
                    {
                        "type": "string",
                        "description": "token",
                        "name": "token",
                        "in": "header",
                        "required": true
                    },
                    {
                        "type": "string",
                        "description": "关键字",
                        "name": "key",
                        "in": "query"
                    },
                    {
                        "type": "integer",
                        "description": "页码",
                        "name": "page",
                        "in": "query"
                    },
                    {
                        "type": "integer",
                        "description": "每页数量",
                        "name": "limit",
                        "in": "query"
                    }
                ],
                "responses": {
                    "200": {
                        "description": "OK",
                        "schema": {
                            "type": "string"
                        }
                    },
                    "400": {
                        "description": "Bad Request",
                        "schema": {
                            "type": "string"
                        }
                    }
                }
            }
        },
        "/api/v1/user/update": {
            "post": {
                "description": "更新用户信息",
                "summary": "更新用户信息",
                "parameters": [
                    {
                        "type": "string",
                        "description": "token",
                        "name": "token",
                        "in": "header",
                        "required": true
                    },
                    {
                        "type": "string",
                        "description": "密码",
                        "name": "password",
                        "in": "formData"
                    },
                    {
                        "type": "string",
                        "description": "邮箱",
                        "name": "email",
                        "in": "formData"
                    },
                    {
                        "type": "string",
                        "description": "手机号",
                        "name": "mobile",
                        "in": "formData"
                    },
                    {
                        "type": "string",
                        "description": "头像地址",
                        "name": "avatar",
                        "in": "formData"
                    },
                    {
                        "type": "string",
                        "description": "个性签名",
                        "name": "signature",
                        "in": "formData"
                    }
                ],
                "responses": {
                    "200": {
                        "description": "OK",
                        "schema": {
                            "type": "string"
                        }
                    },
                    "400": {
                        "description": "Bad Request",
                        "schema": {
                            "type": "string"
                        }
                    }
                }
            }
        },
        "/api/v1/user/upload/avatar": {
            "post": {
                "description": "上传头像",
                "summary": "上传头像",
                "parameters": [
                    {
                        "type": "string",
                        "description": "token",
                        "name": "token",
                        "in": "header",
                        "required": true
                    },
                    {
                        "type": "file",
                        "description": "头像",
                        "name": "avatar",
                        "in": "formData",
                        "required": true
                    }
                ],
                "responses": {
                    "200": {
                        "description": "OK",
                        "schema": {
                            "type": "string"
                        }
                    },
                    "400": {
                        "description": "Bad Request",
                        "schema": {
                            "type": "string"
                        }
                    }
                }
            }
        },
        "/api/v1/user/upload/avatar/abolish": {
            "post": {
                "description": "取消头像上传",
                "summary": "取消头像上传",
                "parameters": [
                    {
                        "type": "string",
                        "description": "token",
                        "name": "token",
                        "in": "header",
                        "required": true
                    },
                    {
                        "type": "integer",
                        "description": "用户id",
                        "name": "user_id",
                        "in": "formData",
                        "required": true
                    }
                ],
                "responses": {
                    "200": {
                        "description": "OK",
                        "schema": {
                            "type": "string"
                        }
                    },
                    "400": {
                        "description": "Bad Request",
                        "schema": {
                            "type": "string"
                        }
                    }
                }
            }
        },
        "/api/v1/video/increase": {
            "get": {
                "description": "获取月总日视频发布数增长记录列表",
                "summary": "获取月总日视频发布数增长记录列表",
                "parameters": [
                    {
                        "type": "string",
                        "description": "token",
                        "name": "token",
                        "in": "header",
                        "required": true
                    },
                    {
                        "type": "string",
                        "description": "年份",
                        "name": "year",
                        "in": "query",
                        "required": true
                    },
                    {
                        "type": "string",
                        "description": "月份",
                        "name": "month",
                        "in": "query",
                        "required": true
                    }
                ],
                "responses": {
                    "200": {
                        "description": "OK",
                        "schema": {
                            "type": "string"
                        }
                    },
                    "400": {
                        "description": "Bad Request",
                        "schema": {
                            "type": "string"
                        }
                    }
                }
            }
        },
        "/api/v1/video/info": {
            "get": {
                "description": "获取视频信息",
                "summary": "获取视频信息",
                "parameters": [
                    {
                        "type": "string",
                        "description": "token",
                        "name": "token",
                        "in": "header",
                        "required": true
                    },
                    {
                        "type": "integer",
                        "description": "视频id",
                        "name": "id",
                        "in": "query",
                        "required": true
                    }
                ],
                "responses": {
                    "200": {
                        "description": "OK",
                        "schema": {
                            "type": "string"
                        }
                    },
                    "400": {
                        "description": "Bad Request",
                        "schema": {
                            "type": "string"
                        }
                    }
                }
            }
        },
        "/api/v1/video/list": {
            "get": {
                "description": "获取用户发布视频列表",
                "summary": "获取用户发布视频列表",
                "parameters": [
                    {
                        "type": "string",
                        "description": "token",
                        "name": "token",
                        "in": "header",
                        "required": true
                    },
                    {
                        "type": "integer",
                        "description": "用户id",
                        "name": "user_id",
                        "in": "query",
                        "required": true
                    }
                ],
                "responses": {
                    "200": {
                        "description": "OK",
                        "schema": {
                            "type": "string"
                        }
                    },
                    "400": {
                        "description": "Bad Request",
                        "schema": {
                            "type": "string"
                        }
                    }
                }
            }
        },
        "/api/v1/video/publish": {
            "post": {
                "description": "保存视频",
                "summary": "保存视频",
                "parameters": [
                    {
                        "type": "string",
                        "description": "token",
                        "name": "token",
                        "in": "header",
                        "required": true
                    },
                    {
                        "type": "string",
                        "description": "标题",
                        "name": "title",
                        "in": "formData",
                        "required": true
                    },
                    {
                        "type": "string",
                        "description": "视频地址",
                        "name": "video_url",
                        "in": "formData",
                        "required": true
                    },
                    {
                        "type": "string",
                        "description": "封面地址",
                        "name": "cover_image_url",
                        "in": "formData",
                        "required": true
                    }
                ],
                "responses": {
                    "200": {
                        "description": "OK",
                        "schema": {
                            "type": "string"
                        }
                    },
                    "400": {
                        "description": "Bad Request",
                        "schema": {
                            "type": "string"
                        }
                    }
                }
            }
        },
        "/api/v1/video/upload/abolish": {
            "post": {
                "description": "取消视频上传",
                "summary": "取消视频上传",
                "parameters": [
                    {
                        "type": "string",
                        "description": "token",
                        "name": "token",
                        "in": "header",
                        "required": true
                    },
                    {
                        "type": "string",
                        "description": "标题",
                        "name": "title",
                        "in": "formData",
                        "required": true
                    },
                    {
                        "type": "boolean",
                        "description": "是否有视频",
                        "name": "haveVideo",
                        "in": "formData",
                        "required": true
                    },
                    {
                        "type": "boolean",
                        "description": "是否有封面",
                        "name": "haveCoverImage",
                        "in": "formData",
                        "required": true
                    }
                ],
                "responses": {
                    "200": {
                        "description": "OK",
                        "schema": {
                            "type": "string"
                        }
                    },
                    "400": {
                        "description": "Bad Request",
                        "schema": {
                            "type": "string"
                        }
                    }
                }
            }
        },
        "/api/v1/video/upload/image": {
            "post": {
                "description": "上传视频封面",
                "summary": "上传视频封面",
                "parameters": [
                    {
                        "type": "string",
                        "description": "token",
                        "name": "token",
                        "in": "header",
                        "required": true
                    },
                    {
                        "type": "file",
                        "description": "封面图片",
                        "name": "cover_image_data",
                        "in": "formData",
                        "required": true
                    },
                    {
                        "type": "string",
                        "description": "标题",
                        "name": "title",
                        "in": "formData",
                        "required": true
                    }
                ],
                "responses": {
                    "200": {
                        "description": "OK",
                        "schema": {
                            "type": "string"
                        }
                    },
                    "400": {
                        "description": "Bad Request",
                        "schema": {
                            "type": "string"
                        }
                    }
                }
            }
        },
        "/api/v1/video/upload/video": {
            "post": {
                "description": "上传视频",
                "summary": "上传视频",
                "parameters": [
                    {
                        "type": "string",
                        "description": "token",
                        "name": "token",
                        "in": "header",
                        "required": true
                    },
                    {
                        "type": "file",
                        "description": "视频文件",
                        "name": "data",
                        "in": "formData",
                        "required": true
                    },
                    {
                        "type": "string",
                        "description": "标题",
                        "name": "title",
                        "in": "formData",
                        "required": true
                    }
                ],
                "responses": {
                    "200": {
                        "description": "OK",
                        "schema": {
                            "type": "string"
                        }
                    },
                    "400": {
                        "description": "Bad Request",
                        "schema": {
                            "type": "string"
                        }
                    }
                }
            }
        }
    },
    "definitions": {
        "api.Response": {
            "type": "object",
            "properties": {
                "code": {
                    "type": "integer"
                },
                "data": {},
                "msg": {
                    "type": "string"
                },
                "total": {
                    "type": "integer"
                }
            }
        }
    }
}